usb_iss/__init__.py
usb_iss/defs.py
usb_iss/driver.py
usb_iss/exceptions.py
usb_iss/i2c.py
usb_iss/io.py
usb_iss/serial_.py
usb_iss/spi.py
usb_iss/usb_iss.py
usb_iss-2.0.1.dist-info/LICENSE
usb_iss-2.0.1.dist-info/METADATA
usb_iss-2.0.1.dist-info/WHEEL
usb_iss-2.0.1.dist-info/top_level.txt
usb_iss-2.0.1.dist-info/RECORD
