Metadata-Version: 2.1
Name: usb-iss
Version: 2.0.1
Summary: Python library for the USB-ISS board.
Home-page: https://github.com/sneakypete81/usb_iss
Author: Pete Burgers
Author-email: sneakypete81@gmail.com
License: GNU General Public License v3
Keywords: usb_iss
Platform: UNKNOWN
Classifier: Development Status :: 5 - Production/Stable
Classifier: Intended Audience :: Developers
Classifier: License :: OSI Approved :: GNU General Public License v3 (GPLv3)
Classifier: Natural Language :: English
Classifier: Programming Language :: Python :: 2
Classifier: Programming Language :: Python :: 2.7
Classifier: Programming Language :: Python :: 3
Classifier: Programming Language :: Python :: 3.5
Classifier: Programming Language :: Python :: 3.6
Classifier: Programming Language :: Python :: 3.7
License-File: LICENSE
Requires-Dist: pyserial
Requires-Dist: enum34 ; python_version == "2.7"
